{
  "default": "en",
  "en": {
    "popup": {
      "title": "UPORTAL links",
      "tagFilterPlaceholder": "tags...",
      "refreshTitle": "Refresh dictionary",
      "noUportal": "Send this email without UPORTAL",
      "copyClientUidTitle": "Copy plugin UID",
      "uidButton": "UID",
      "uidCopiedButton": "OK",
      "loading": "Loading dictionary...",
      "empty": "No links match this filter.",
      "insertSelected": "Insert selected",
      "insert": "Insert",
      "defaultAnchor": "link"
    },
    "options": {
      "title": "UPORTAL settings",
      "heading": "UPORTAL Link Inserter",
      "apiBase": "API base URL",
      "userToken": "X-User-Token",
      "clientUid": "Client UID",
      "copyClientUidTitle": "Copy UID",
      "pixelBaseUrl": "Pixel base URL",
      "dictionaryUrl": "Dictionary URL",
      "defaultMailFrom": "Mail fallback when recipients are empty",
      "pixelTokenPrefix": "Pixel token prefix",
      "save": "Save",
      "testDictionary": "Test dictionary",
      "apiBasePlaceholder": "http://localhost:8080",
      "userTokenPlaceholder": "user token",
      "pixelBaseUrlPlaceholder": "empty means API base URL",
      "dictionaryUrlPlaceholder": "http://localhost:8080/api/admin/dictionary",
      "defaultMailFromPlaceholder": "no-reply@example.com",
      "pixelTokenPrefixPlaceholder": "mail-pixel",
      "saved": "Saved.",
      "uidCopied": "UID copied.",
      "serverSource": "server"
    },
    "confirm": {
      "title": "UPORTAL unavailable",
      "heading": "UPORTAL unavailable",
      "body": "The server did not respond or returned an error. Tracking links and pixel cannot be created right now.",
      "sendPlain": "Send without UPORTAL links",
      "saveDraft": "Save to drafts",
      "hint": "If you choose draft, sending will be canceled. The email will stay in the compose window; the extension will also try to save it as Draft.",
      "defaultError": "Server unavailable"
    },
    "background": {
      "defaultLinkText": "Open link",
      "defaultDictionaryAnchor": "Link {index}",
      "timeout": "UPORTAL: server did not respond within {seconds} sec.",
      "shortUrlExtractFailed": "Could not extract short URL from API response",
      "defaultSubject": "No subject",
      "redirectUrlMissing": "UPORTAL: redirect link has no url: {id}",
      "dictionaryLinkMissing": "UPORTAL: link not found in dictionary: {id}"
    }
  },
  "ru": {
    "popup": {
      "title": "UPORTAL ссылки",
      "tagFilterPlaceholder": "тэги...",
      "refreshTitle": "Освежить словарь",
      "noUportal": "Отправить это письмо без UPORTAL",
      "copyClientUidTitle": "Скопировать UID плагина",
      "uidButton": "UID",
      "uidCopiedButton": "OK",
      "loading": "Загрузка словаря...",
      "empty": "Нет ссылок под этот фильтр.",
      "insertSelected": "Вставить выбранные",
      "insert": "Вставить",
      "defaultAnchor": "ссылка"
    },
    "options": {
      "title": "UPORTAL настройки",
      "heading": "UPORTAL Link Inserter",
      "apiBase": "API base URL",
      "userToken": "X-User-Token",
      "clientUid": "UID клиента",
      "copyClientUidTitle": "Скопировать UID",
      "pixelBaseUrl": "Pixel base URL",
      "dictionaryUrl": "URL словаря",
      "defaultMailFrom": "Mail fallback, если получателей нет",
      "pixelTokenPrefix": "Префикс token для pixel",
      "save": "Сохранить",
      "testDictionary": "Проверить словарь",
      "apiBasePlaceholder": "http://localhost:8080",
      "userTokenPlaceholder": "user token",
      "pixelBaseUrlPlaceholder": "если пусто - API base URL",
      "dictionaryUrlPlaceholder": "http://localhost:8080/api/admin/dictionary",
      "defaultMailFromPlaceholder": "no-reply@example.com",
      "pixelTokenPrefixPlaceholder": "mail-pixel",
      "saved": "Сохранено.",
      "uidCopied": "UID скопирован.",
      "serverSource": "сервер"
    },
    "confirm": {
      "title": "UPORTAL недоступен",
      "heading": "UPORTAL недоступен",
      "body": "Сервер не ответил или вернул ошибку. Трекинговые ссылки и pixel сейчас создать нельзя.",
      "sendPlain": "Отправить без UPORTAL-ссылок",
      "saveDraft": "Сохранить в черновиках",
      "hint": "Если выбрать черновик, отправка будет отменена. Письмо останется в окне compose; расширение также попробует сохранить его как Draft.",
      "defaultError": "Сервер недоступен"
    },
    "background": {
      "defaultLinkText": "Открыть ссылку",
      "defaultDictionaryAnchor": "Ссылка {index}",
      "timeout": "UPORTAL: сервер не ответил за {seconds} сек.",
      "shortUrlExtractFailed": "Не удалось извлечь short URL из ответа API",
      "defaultSubject": "Без темы",
      "redirectUrlMissing": "UPORTAL: у redirect-ссылки нет url: {id}",
      "dictionaryLinkMissing": "UPORTAL: ссылка не найдена в словаре: {id}"
    }
  },
  "es": {
    "popup": {
      "title": "Enlaces UPORTAL",
      "tagFilterPlaceholder": "etiquetas...",
      "refreshTitle": "Actualizar diccionario",
      "noUportal": "Enviar este correo sin UPORTAL",
      "copyClientUidTitle": "Copiar UID del plugin",
      "uidButton": "UID",
      "uidCopiedButton": "OK",
      "loading": "Cargando diccionario...",
      "empty": "No hay enlaces para este filtro.",
      "insertSelected": "Insertar seleccionados",
      "insert": "Insertar",
      "defaultAnchor": "enlace"
    },
    "options": {
      "title": "Configuracion de UPORTAL",
      "heading": "UPORTAL Link Inserter",
      "apiBase": "URL base de API",
      "userToken": "X-User-Token",
      "clientUid": "UID del cliente",
      "copyClientUidTitle": "Copiar UID",
      "pixelBaseUrl": "URL base del pixel",
      "dictionaryUrl": "URL del diccionario",
      "defaultMailFrom": "Email fallback si no hay destinatarios",
      "pixelTokenPrefix": "Prefijo del token de pixel",
      "save": "Guardar",
      "testDictionary": "Probar diccionario",
      "apiBasePlaceholder": "http://localhost:8080",
      "userTokenPlaceholder": "token de usuario",
      "pixelBaseUrlPlaceholder": "vacio significa URL base de API",
      "dictionaryUrlPlaceholder": "http://localhost:8080/api/admin/dictionary",
      "defaultMailFromPlaceholder": "no-reply@example.com",
      "pixelTokenPrefixPlaceholder": "mail-pixel",
      "saved": "Guardado.",
      "uidCopied": "UID copiado.",
      "serverSource": "servidor"
    },
    "confirm": {
      "title": "UPORTAL no disponible",
      "heading": "UPORTAL no disponible",
      "body": "El servidor no respondio o devolvio un error. Ahora no se pueden crear enlaces de seguimiento ni pixel.",
      "sendPlain": "Enviar sin enlaces UPORTAL",
      "saveDraft": "Guardar en borradores",
      "hint": "Si eliges borrador, el envio se cancelara. El correo quedara en la ventana de redaccion; la extension tambien intentara guardarlo como borrador.",
      "defaultError": "Servidor no disponible"
    },
    "background": {
      "defaultLinkText": "Abrir enlace",
      "defaultDictionaryAnchor": "Enlace {index}",
      "timeout": "UPORTAL: el servidor no respondio en {seconds} seg.",
      "shortUrlExtractFailed": "No se pudo extraer el short URL de la respuesta de API",
      "defaultSubject": "Sin asunto",
      "redirectUrlMissing": "UPORTAL: el enlace redirect no tiene url: {id}",
      "dictionaryLinkMissing": "UPORTAL: enlace no encontrado en el diccionario: {id}"
    }
  }
}
